Metadata-Version: 1.1
Name: PyDiscordBot
Version: 0.0.0
Summary: A very basic discord bot for begginer
Home-page: UNKNOWN
Author: LeftandRight
Author-email: wempaleft@gmail.com
License: MIT
Keywords: BOT
Platform: UNKNOWN
Classifier: Development Status :: 5 - Production/Stable
Classifier: Intended Audience :: Education
Classifier: Operating System :: Microsoft :: Windows :: Windows 10
Classifier: License :: OSI Approved :: MIT License
Classifier: Programming Language :: Python :: 3
